LICENSE
MANIFEST.in
README.rst
setup.py
StructuredData/Classes.py
StructuredData/SDshelllib.py
StructuredData/SDshelllibBase.py
StructuredData/SDshelllibFun.py
StructuredData/SDshelllibTxt.py
StructuredData/SDshellrpclib.py
StructuredData/__init__.py
StructuredData/data/SDpyshell.rst
StructuredData/internal/ManagedStore.py
StructuredData/internal/Repr.py
StructuredData/internal/__init__.py
StructuredData/internal/dictutils.py
StructuredData/internal/enumclass.py
StructuredData/internal/lock.py
StructuredData/internal/myyaml.py
StructuredData/internal/password.py
StructuredData/internal/processes.py
StructuredData/internal/rst_load.py
StructuredData/internal/telnetserver.py
bin/SDpyshell
bin/SDview
bin/SDxmlrpc
doc/SDpyshell.rst
doc/SDpyshell_examples.rst
doc/SDview.rst
doc/SDxmlrpc.rst
doc/examples.rst
doc/index.rst
doc/install.rst
doc/introduction.rst
doc/license.rst
doc/python_modules.rst
doc/reference.rst
doc/_build/html/.buildinfo
doc/_build/html/SDpyshell.html
doc/_build/html/SDpyshell_examples.html
doc/_build/html/SDview.html
doc/_build/html/SDxmlrpc.html
doc/_build/html/examples.html
doc/_build/html/genindex.html
doc/_build/html/index.html
doc/_build/html/install.html
doc/_build/html/introduction.html
doc/_build/html/license.html
doc/_build/html/objects.inv
doc/_build/html/py-modindex.html
doc/_build/html/python_modules.html
doc/_build/html/reference.html
doc/_build/html/search.html
doc/_build/html/searchindex.js
doc/_build/html/_images/SDview-idcp_db-expanded.png
doc/_build/html/_images/SDview-idcp_db-initialwin.png
doc/_build/html/_images/SDview-small-collapse-all.png
doc/_build/html/_images/SDview-small-collapse.png
doc/_build/html/_images/SDview-small-expand-all.png
doc/_build/html/_images/SDview-small-expand.png
doc/_build/html/_images/SDview-small-initialwin.png
doc/_build/html/_images/SDview-small-pattern-result1.png
doc/_build/html/_images/SDview-small-pattern-result2.png
doc/_build/html/_images/SDview-small-pattern1.png
yaml_structureddata.egg-info/PKG-INFO
yaml_structureddata.egg-info/SOURCES.txt
yaml_structureddata.egg-info/dependency_links.txt
yaml_structureddata.egg-info/requires.txt
yaml_structureddata.egg-info/top_level.txt